[
     {
      "region": "Thiruvallur",
      "totalInfected": 33,
      "recovered": 33,
      "deceased": 0,
      "uptime":"25-05-2020"
    },
    {
      "region": "Andhra Pradesh",
      "totalInfected": 2757,
      "recovered": 1809,
      "deceased": 56
    },
    {
      "region": "Arunachal Pradesh",
      "totalInfected": 1,
      "recovered": 1,
      "deceased": 0
    },
    {
      "region": "Assam",
      "totalInfected": 329,
      "recovered": 55,
      "deceased": 4
    },
    {
      "region": "Bihar",
      "totalInfected": 2380,
      "recovered": 653,
      "deceased": 11
    },
    {
      "region": "Chandigarh",
      "totalInfected": 225,
      "recovered": 179,
      "deceased": 3
    },
    {
      "region": "Chhattisgarh",
      "totalInfected": 214,
      "recovered": 64,
      "deceased": 0
    },
    {
      "region": "Dadar Nagar Haveli",
      "totalInfected": 2,
      "recovered": 0,
      "deceased": 0
    },
    {
      "region": "Delhi",
      "totalInfected": 12910,
      "recovered": 6267,
      "deceased": 231
    },
    {
      "region": "Goa",
      "totalInfected": 55,
      "recovered": 16,
      "deceased": 0
    },
    {
      "region": "Gujarat",
      "totalInfected": 13664,
      "recovered": 6169,
      "deceased": 829
    },
    {
      "region": "Haryana",
      "totalInfected": 1131,
      "recovered": 750,
      "deceased": 16
    },
    {
      "region": "Himachal Pradesh",
      "totalInfected": 185,
      "recovered": 61,
      "deceased": 3
    },
    {
      "region": "Jammu and Kashmir",
      "totalInfected": 1569,
      "recovered": 774,
      "deceased": 21
    },
    {
      "region": "Jharkhand",
      "totalInfected": 350,
      "recovered": 141,
      "deceased": 4
    },
    {
      "region": "Karnataka",
      "totalInfected": 1959,
      "recovered": 608,
      "deceased": 42
    },
    {
      "region": "Kerala",
      "totalInfected": 795,
      "recovered": 515,
      "deceased": 4
    },
    {
      "region": "Ladakh",
      "totalInfected": 49,
      "recovered": 43,
      "deceased": 0
    },
    {
      "region": "Madhya Pradesh",
      "totalInfected": 6371,
      "recovered": 3267,
      "deceased": 281
    },
    {
      "region": "Maharashtra",
      "totalInfected": 47190,
      "recovered": 13404,
      "deceased": 1577
    },
    {
      "region": "Manipur",
      "totalInfected": 29,
      "recovered": 4,
      "deceased": 0
    },
    {
      "region": "Meghalaya",
      "totalInfected": 14,
      "recovered": 12,
      "deceased": 1
    },
    {
      "region": "Mizoram",
      "totalInfected": 1,
      "recovered": 1,
      "deceased": 0
    },
    {
      "region": "Odisha",
      "totalInfected": 1269,
      "recovered": 497,
      "deceased": 7
    },
    {
      "region": "Puducherry",
      "totalInfected": 26,
      "recovered": 10,
      "deceased": 0
    },
    {
      "region": "Punjab",
      "totalInfected": 2045,
      "recovered": 1870,
      "deceased": 39
    },
    {
      "region": "Rajasthan",
      "totalInfected": 6742,
      "recovered": 3786,
      "deceased": 160
    },
    {
      "region": "Sikkim",
      "totalInfected": 1,
      "recovered": 0,
      "deceased": 0
    },
    {
      "region": "Tamil Nadu",
      "totalInfected": 15512,
      "recovered": 7491,
      "deceased": 103
    },
    {
      "region": "Telengana",
      "totalInfected": 1813,
      "recovered": 1065,
      "deceased": 49
    },
    {
      "region": "Tripura",
      "totalInfected": 189,
      "recovered": 153,
      "deceased": 0
    },
    {
      "region": "Uttarakhand",
      "totalInfected": 244,
      "recovered": 56,
      "deceased": 2
    },
    {
      "region": "Uttar Pradesh",
      "totalInfected": 6017,
      "recovered": 3406,
      "deceased": 155
    },
    {
      "region": "West Bengal",
      "totalInfected": 3459,
      "recovered": 1281,
      "deceased": 269
    },
    {
      "region": "Cases being reassigned to states",
      "totalInfected": 2338,
      "recovered": 0,
      "deceased": 0
    }
]
